lambdo.py
lambdo-6.2.4.dist-info/entry_points.txt
lambdo-6.2.4.dist-info/WHEEL
lambdo-6.2.4.dist-info/METADATA
lambdo-6.2.4.dist-info/RECORD
