Metadata-Version: 2.1
Name: lambdo
Version: 6.2.4
Summary: Humor is the only test of gravity, and gravity of humor; for a subject which will not bear raillery is suspicious, and a jest which will not bear serious examination is false wit.
Home-page: https://github.com/jvhellemond/lambdo
Author: Jan van Hellemond
Author-email: jan@jvhellemond.nl
Requires-Python: >=3.9,<4.0
Classifier: Programming Language :: Python :: 3
Classifier: Programming Language :: Python :: 3.10
Classifier: Programming Language :: Python :: 3.9
Requires-Dist: PyYAML (>=6.0,<7.0)
Requires-Dist: boto3 (>=1.20.52,<2.0.0)
Requires-Dist: glob2 (>=0.7,<0.8)
Project-URL: Repository, https://github.com/jvhellemond/lambdo
